chatbot/__init__.py
chatbot/bots.py
chatbot/chat.py
chatbot/client.py
chatbot/example.py
chatbot/settings.py
chatbot/skeleton.py
chatbot/utils.py
chatbot/contrib/__init__.py
chatbot/contrib/base.py
chatbot/contrib/humor.py
chatbot/contrib/random.py
chatbot/contrib/simple.py
chatbot/contrib/twitter.py
chatbot/contrib/urls.py
python_chatbot-0.0.10.dist-info/AUTHORS.rst
python_chatbot-0.0.10.dist-info/LICENSE.txt
python_chatbot-0.0.10.dist-info/METADATA
python_chatbot-0.0.10.dist-info/WHEEL
python_chatbot-0.0.10.dist-info/top_level.txt
python_chatbot-0.0.10.dist-info/RECORD
