Metadata-Version: 2.1
Name: python-chatbot
Version: 0.0.10
Summary: Extensible IRC chatbot written in python.
Home-page: https://pyscaffold.org/
Author: harrislapiroff
Author-email: harris@chromamine.com
License: mit
Platform: any
Classifier: Development Status :: 4 - Beta
Classifier: Programming Language :: Python
Requires-Dist: service-identity
Requires-Dist: twisted
Provides-Extra: testing
Requires-Dist: pytest ; extra == 'testing'
Requires-Dist: pytest-cov ; extra == 'testing'
